MANIFEST.in
README.txt
setup.cfg
setup.py
docs/HISTORY.txt
docs/INSTALL.txt
docs/LICENSE.GPL
docs/LICENSE.txt
ityou/__init__.py
ityou.portlets.egg-info/PKG-INFO
ityou.portlets.egg-info/SOURCES.txt
ityou.portlets.egg-info/dependency_links.txt
ityou.portlets.egg-info/entry_points.txt
ityou.portlets.egg-info/namespace_packages.txt
ityou.portlets.egg-info/not-zip-safe
ityou.portlets.egg-info/paster_plugins.txt
ityou.portlets.egg-info/requires.txt
ityou.portlets.egg-info/top_level.txt
ityou/portlets/__init__.py
ityou/portlets/colors.py
ityou/portlets/configure.zcml
ityou/portlets/data_digger.py
ityou/portlets/tests.py
ityou/portlets/translate.ityou.portlets.sh
ityou/portlets/locales/ityou.portlets.pot
ityou/portlets/locales/de/LC_MESSAGES/ityou.portlets.po
ityou/portlets/locales/en/LC_MESSAGES/ityou.portlets.po
ityou/portlets/portlets/__init__.py
ityou/portlets/portlets/availabilitychart.pt
ityou/portlets/portlets/availabilitychart.py
ityou/portlets/portlets/configure.zcml
ityou/portlets/portlets/documentrating.pt
ityou/portlets/portlets/documentrating.py
ityou/portlets/portlets/myfollowers.pt
ityou/portlets/portlets/myfollowers.py
ityou/portlets/portlets/portaltypes-pie.pt
ityou/portlets/portlets/portaltypes-pie.py
ityou/portlets/portlets/releasestates-pie.pt
ityou/portlets/portlets/releasestates-pie.py
ityou/portlets/profiles/default/cssregistry.xml
ityou/portlets/profiles/default/jsregistry.xml
ityou/portlets/profiles/default/metadata.xml
ityou/portlets/profiles/default/portlets.xml
ityou/portlets/resources/portlets.css
ityou/portlets/resources/vendors/d3/d3.v3.min.js
ityou/portlets/resources/vendors/d3/c3/c3.css
ityou/portlets/resources/vendors/d3/c3/c3.min.js
ityou/portlets/resources/vendors/d3/d3pie/d3pie.min.js
ityou/portlets/tests/__init__.py
ityou/portlets/tests/base_avaiabilitychart.py
ityou/portlets/tests/base_availabilitychart.py
ityou/portlets/tests/base_contenttypespie.py
ityou/portlets/tests/base_documentrating.py
ityou/portlets/tests/base_myfollowers.py
ityou/portlets/tests/test_avaiabilitychart.py
ityou/portlets/tests/test_availabilitychart.py
ityou/portlets/tests/test_contenttypespie.py
ityou/portlets/tests/test_documentrating.py
ityou/portlets/tests/test_myfollowers.py