Metadata-Version: 1.1
Name: ityou.portlets
Version: 1.3b2
Summary: ITYOU ESI - Portlets
Home-page: http://www.ityou.de/esi/
Author: ITYOU/LM
Author-email: lm@ityou.de
License: GPL
Platform: UNKNOWN
Classifier: Framework :: Plone
Classifier: Programming Language :: Python
